slrm/__init__.py
slrm/launcher.py
slrm-0.0.1.dist-info/LICENSE
slrm-0.0.1.dist-info/METADATA
slrm-0.0.1.dist-info/WHEEL
slrm-0.0.1.dist-info/top_level.txt
slrm-0.0.1.dist-info/RECORD
